odoo/addons/ce/__init__.py
odoo/addons/ce/__manifest__.py
odoo/addons/ce/controllers/__init__.py
odoo/addons/ce/controllers/controllers.py
odoo/addons/ce/controllers/website_subscription_main.py
odoo/addons/ce/data/auth_keycloak_data.xml
odoo/addons/ce/data/crm_lead_tag.xml
odoo/addons/ce/data/crm_maps_data.xml
odoo/addons/ce/data/ir_config_parameter_data.xml
odoo/addons/ce/data/mail_template_data.xml
odoo/addons/ce/data/mail_template_update_data.xml
odoo/addons/ce/data/res_company_data.xml
odoo/addons/ce/data/res_groups_data.xml
odoo/addons/ce/data/utm_data.xml
odoo/addons/ce/demo/demo_data.xml
odoo/addons/ce/i18n/ca_ES.po
odoo/addons/ce/i18n/es.po
odoo/addons/ce/i18n_extra/ca_ES.po
odoo/addons/ce/i18n_extra/es.po
odoo/addons/ce/models/__init__.py
odoo/addons/ce/models/account_invoice.py
odoo/addons/ce/models/auth_oauth_provider.py
odoo/addons/ce/models/cm_place.py
odoo/addons/ce/models/crm_lead.py
odoo/addons/ce/models/keycloak_sync_wiz.py
odoo/addons/ce/models/product.py
odoo/addons/ce/models/res_company.py
odoo/addons/ce/models/res_config_settings.py
odoo/addons/ce/models/res_groups.py
odoo/addons/ce/models/res_partner.py
odoo/addons/ce/models/res_users.py
odoo/addons/ce/models/res_users_role.py
odoo/addons/ce/models/subscription_request.py
odoo/addons/ce/models/utm_source.py
odoo/addons/ce/security/ir_rules_data.xml
odoo/addons/ce/services/__init__.py
odoo/addons/ce/services/ce_community_service.py
odoo/addons/ce/services/ce_member_profile_service.py
odoo/addons/ce/services/ce_member_service.py
odoo/addons/ce/services/crm_lead_service.py
odoo/addons/ce/services/schemas.py
odoo/addons/ce/static/description/icon.png
odoo/addons/ce/tests/__init__.py
odoo/addons/ce/tests/common.py
odoo/addons/ce/tests/common_service.py
odoo/addons/ce/tests/test_crm_lead_service.py
odoo/addons/ce/views/auth_oauth_provider_views.xml
odoo/addons/ce/views/ce_views.xml
odoo/addons/ce/views/cm_place.xml
odoo/addons/ce/views/crm_lead_views.xml
odoo/addons/ce/views/menus.xml
odoo12_addon_ce-12.0.0.0.17.dist-info/METADATA
odoo12_addon_ce-12.0.0.0.17.dist-info/WHEEL
odoo12_addon_ce-12.0.0.0.17.dist-info/top_level.txt
odoo12_addon_ce-12.0.0.0.17.dist-info/RECORD
