Metadata-Version: 2.1
Name: odoo12-addon-ce
Version: 12.0.0.0.17
Summary: Comunitats Energètiques customizations
Home-page: https://somenergia.coop
Author: Coopdevs Treball SCCL & Som Energia SCCL
License: AGPL-3
Platform: UNKNOWN
Classifier: Programming Language :: Python
Classifier: Framework :: Odoo
Classifier: Framework :: Odoo :: 12.0
Classifier: License :: OSI Approved :: GNU Affero General Public License v3
Requires-Python: >=3.5
Requires-Dist: odoo12-addon-auth-api-key
Requires-Dist: odoo12-addon-auth-keycloak
Requires-Dist: odoo12-addon-base-rest
Requires-Dist: odoo12-addon-base-rest-base-structure
Requires-Dist: odoo12-addon-base-user-role
Requires-Dist: odoo12-addon-community-maps
Requires-Dist: odoo12-addon-l10n-es-cooperator
Requires-Dist: odoo (<12.1dev,>=12.0a)
